single core/XRISC_single.sv
//Top-level Module
module top(input         clk, reset, 
           output [31:0] WriteData, DataAdr, 
           output        MemWrite);

  logic [31:0] PC, Instr, ReadData;
  
  // instantiate processor and memories
  XRISC_single XRISC(clk, reset, PC, Instr, MemWrite, DataAdr, WriteData, ReadData);
  imem imem(PC, Instr);
  dmem dmem(clk, Memwrite, DataAdr, WriteData, ReadData);
endmodule

//Single-cycle RISC-V processor
module XRISC_single(input  logic        clk,reset,
                    output logic [31:0] PC,
                    input  logic [31:0] Instr,
                    output logic        MemWrite,
                    output logic [31:0] ALUResult,WriteData,
                    input  logic [31:0] ReadData);

    logic ALUSrc, RegWrite, Jump, Zero;
    logic [1:0] ResultSrc, ImmSrc;
    logic [3:0] ALUControl;

    controller c(Instr[6:0],Instr[14:12],Instr[31:25], Zero, ResultSrc, MemWrite, PCSrc, ALUSrc, RegWrite, Jump, ImmSrc, ALUControl);

    datapath dp(clk, reset, ResultSrc, PCSrc, ALUSrc, RegWrite, ImmSrc, ALUControl, Zero, PC, Instr, ALUResult, WriteData, ReadData);

endmodule

//Controller
module controller(  input logic [6:0] op,
                    input logic [2:0] funct3,
                    input logic [6:0] funct7,
                    input logic       Zero,
                    output logic [1:0] ResultSrc,
                    output logic       MemWrite,
                    output logic       PCSrc, ALUSrc,
                    output logic       RegWrite, Jump,
                    output logic [1:0] ImmSrc,
                    output logic [3:0] ALUControl);
    logic [1:0] ALUOp;
    logic Branch;

    Main_decoder md(op, ResultSrc,MemWrite, Branch, ALUSrc, RegWrite, Jump, ImmSrc, ALUOp);
    ALU_decoder ad(ALUOp, funct3, op[5], funct7, ALUControl);

    assign PCSrc = (Branch & Zero) | Jump;
endmodule

//Main decoder
module Main_decoder(input logic [6:0] op,
                    output logic [1:0] ResultSrc,
                    output logic       MemWrite,
                    output logic       Branch, ALUSrc,
                    output logic       RegWrite, Jump,
                    output logic [1:0] ImmSrc,
                    output logic [1:0] ALUOp);
    logic [10:0] controls;

    assign {RegWrite, ImmSrc, ALUSrc, MemWrite, ResultSrc, Branch, ALUOp, Jump} = controls;

    always_comb  
    
        case(op)
        //RegWrite_ImmSrc_ALUSrc_MemWrite_ResultSrc_Branch_ALUOp_Jump
        7'b0000011: controls = 11'b1_00_1_0_01_0_00_0; //lw
        7'b0100011: controls = 11'b0_01_1_1_00_0_00_0; //sw
        7'b0110011: controls = 11'b1_xx_0_0_00_0_10_0; //R-type
        7'b1100011: controls = 11'b0_10_0_0_00_1_01_0; //beq
        7'b0010011: controls = 11'b1_00_1_0_00_0_10_0; //I-type ALU
        7'b1101111: controls = 11'b1_11_0_0_10_0_00_1; //jal
        default:    controls = 11'bx_xx_x_x_xx_x_xx_x; //???

     //   default:    controls = 11'bx_xx_x_x_xx_x_xx_x; //???
        endcase
endmodule

//ALU decoder
module ALU_decoder(input logic  [1:0] ALUOp,
                    input logic [2:0] funct3,
                    input logic       opb5,
                    input logic [6:0] funct7,                    
                    output logic [3:0] ALUControl);
    
   always_comb

        case(ALUOp)
            2'b00:                      ALUControl = 4'b0000; // performs addition;
            2'b01:                       ALUControl = 4'b0001; // performs subtraction;
            default: case(funct3)
                    3'b000: 
                        case(funct7)
                            7'b0000000:         ALUControl = 4'b0000; // add,addi;
                            7'b0000001:         ALUControl = 4'b1001; // multiply;
                            7'b0100000:         ALUControl = 4'b0001; // R type subtraction;
                        endcase
                    3'b010:                 ALUControl = 4'b0101; // set less than,slti;
                    3'b110:                 ALUControl = 4'b0011; // or,ori;
                    3'b111:                 ALUControl = 4'b0010; // and,andi;
                    3'b100:                 ALUControl = 4'b0100; // divide(signed)
                    3'b101: if (funct7 == 7'b0100000)        
                                            ALUControl = 4'b0110; // shift right arithmetic
                            else
                                            ALUControl = 4'b0111; // shift right logical
                    3'b001:                 ALUControl = 4'b1000; // shift left logical
                    default:                ALUControl = 4'bxxxx; // ???
            endcase
        endcase
endmodule

//Datapath
module datapath(input  logic        clk,reset,
                input  logic [1:0]  ResultSrc,
                input  logic        PCSrc,ALUSrc,
                input  logic        RegWrite,
                input  logic [1:0]  ImmSrc,
                input  logic [3:0]  ALUControl,
                output logic        Zero,
                output logic [31:0] PC,
                input  logic [31:0] Instr,
                output logic [31:0] ALUResult, WriteData,
                input  logic [31:0] ReadData);
    logic [31:0] PCNext, PCPlus4, PCTarget;
    logic [31:0] ImmExt;
    logic [31:0] SrcA, SrcB;
    logic [31:0] Result;

    //next PC logic
    resettable_ff #(32) pcreg(clk, reset, PCNext, PC);
    adder       pcadd4(PC,32'd1, PCPlus4);
    adder       pcaddbranch(PC, ImmExt, PCTarget);
    mux2 #(32)  pcmux(PCPlus4, PCTarget, PCSrc, PCNext);

    //register file logic
    regfile     rf(clk, RegWrite, Instr[19:15], Instr[24:20], Instr[11:7], Result, SrcA, WriteData);
    extendunit      ext(Instr[31:7], ImmSrc, ImmExt);

    //ALU logic
    mux2 #(32)  srcbmux(WriteData,ImmExt, ALUSrc, SrcB);
    alu         alu(SrcA, SrcB, ALUControl, ALUResult, Zero);
    mux3 #(32)  resultmux(ALUResult, ReadData, PCPlus4, ResultSrc, Result);

endmodule

module alu(input logic          [31:0] SrcA,SrcB,  // ALU 32-bit Inputs                 
           input logic          [3:0] ALUControl,// ALU Control signal from ALU decoder
           output logic         [31:0] ALUResult, // ALU 32-bit Output
           output logic         Zero); // Zero Flag
   
    logic [32:0] ALU_Result;
    wire [32:0] tmp;
    assign ALU_Out = ALUResult; // ALU out
    assign tmp = {1'b0,SrcA} + {1'b0,SrcB};
    assign Zero = (ALUResult == 32'b0); // Zero flag
    //assign CarryOut = tmp[32]; // Carryout flag
    
    always_comb
        case(ALUControl)
            4'b0000: // Addition
               ALUResult = SrcA + SrcB ; 
            4'b0001: // Subtraction
               ALUResult = SrcA - SrcB ;
            4'b1001: // Multiplication
               ALUResult = SrcA * SrcB;
            4'b0100: // Division
               ALUResult = SrcA / SrcB;
            4'b1000: // shift left logical
               ALUResult = SrcA << SrcB;
            4'b0111: // Logical shift right
               ALUResult = SrcA >> SrcB;
            4'b0010: //  and 
               ALUResult = SrcA & SrcB;
            4'b0011: //  or
               ALUResult = SrcA | SrcB;
            4'b0111: // shift right arithmetic
               ALUResult = SrcA >>> SrcB;       
            
        endcase
endmodule 

module adder(input logic  [31:0] a,
             input logic  [31:0] b,
             output logic  [31:0] c);
  //logic [32:0] y_test;
    assign c = a + b;
                                
endmodule

module extendunit(input logic [31:7] instr,
                  input logic [1:0]  immsrc,
                  output logic [31:0] immext);
    always@*
        case(immsrc)
            // I type
            2'b00: immext = {{20{instr[31]}}, {instr[31:20]}};
            // S type
            2'b01: immext = {{20{instr[31]}}, {instr[31:25]}, {instr[11:7]}};
            // B type
            2'b10: immext = {{20{instr[31]}}, {instr[7]}, { instr[30:25]}, {instr[11:8]}, 1'b0};
            // J type
            2'b11: immext = {{12{instr[31]}}, {instr[19:12]}, { instr[20]}, {instr[30:21]}, 1'b0};
            default: immext = 32'bx;
        endcase
endmodule

module resettable_ff_enable #(parameter WIDTH = 32)
                (input logic            clk, reset, en,
                 input logic [WIDTH-1:0]d,
                 output logic [WIDTH-1:0]q);
always_ff@(posedge clk, posedge reset)
    if (reset) q <= 0;
    else if (en) q <= d;
endmodule

module resettable_ff #(parameter WIDTH = 32)
                (input logic            clk, reset,
                 input logic [WIDTH-1:0]d,
                 output logic [WIDTH-1:0]q);
always_ff@(posedge clk, posedge reset)
    if (reset)  q <= 0;
    else        q <= d;
endmodule

module mux3 #(parameter WIDTH = 8)
            (input logic [WIDTH-1:0] d0, d1, d2,
            input logic  [1:0]       s,
            output logic [WIDTH-1:0] y);

assign y = s[1] ? d2 : (s[0] ? d1 : d0);
endmodule

module mux2 #(parameter WIDTH = 8)
            (input logic [WIDTH-1:0] d0, d1, 
            input logic              s,
            output logic [WIDTH-1:0] y);

assign y = s ? d1 : d0;
endmodule

//data memory
module dmem(input  logic            clk, we,
            input  logic    [31:0] a, wd,
            output logic    [31:0] rd);

  logic  [31:0] RAM[63:0];

  assign rd = RAM[a[31:2]]; // word aligned

  always @(posedge clk)
    if (we)
      RAM[a[31:2]] <= wd;
endmodule

//instruction memory
module imem(input  logic    [31:0] a,
            output logic    [31:0] rd);

  logic[31:0]RAM[0:40];

  initial
    begin
      $readmemh("riscvtest1.txt",RAM);
    end

  assign rd = RAM[a]; // word aligned
endmodule

module regfile(input logic      clk, 
               input logic           WE3, 
               input logic [4:0]     A1, A2, A3, 
               input logic [31:0]    WD3, 
               output logic [31:0]    RD1, RD2);
    reg [31:0] rf[0:40];
    always @(posedge clk)
        if (WE3) rf[A3] <= WD3;	

    assign RD1 = (A1 != 0) ? rf[A1] : 0;
    assign RD2 = (A2 != 0) ? rf[A2] : 0;
endmodule

single core/XRISC_single_tb.sv
`timescale 1ps/1ps
`include "XRISC_single.sv"

module XRISC_single_tb();

    logic           clk;
    logic           reset;
    logic   [31:0]  WriteData, DataAdr;
    logic           MemWrite;

top dut(clk, reset, WriteData, DataAdr,MemWrite);

//initialize test
initial 
    begin
        reset <= 1;#22; reset <= 0;
    end


initial begin
    $dumpfile("XRISC_single_tb.vcd");
    $dumpvars;
end
    
//generate clock to sequence tests
    always 
    begin        
        clk <= 1; #5; clk <=0; #5;
        clk <= 1; #5; clk <=0; #5;
        clk <= 1; #5; clk <=0; #5;
        clk <= 1; #5; clk <=0; #5;
        clk <= 1; #5; clk <=0; #5;
        clk <= 1; #5; clk <=0; #5;
        clk <= 1; #5; clk <=0; #5;
        clk <= 1; #5; clk <=0; #5;        
        clk <= 1; #5; clk <=0; #5;
        clk <= 1; #5; clk <=0; #5;
        clk <= 1; #5; clk <=0; #5;
        clk <= 1; #5; clk <=0; #5;
        clk <= 1; #5; clk <=0; #5;
        clk <= 1; #5; clk <=0; #5;
        clk <= 1; #5; clk <=0; #5;
        clk <= 1; #5; clk <=0; #5;
        clk <= 1; #5; clk <=0; #5;
        clk <= 1; #5; clk <=0; #5;
        clk <= 1; #5; clk <=0; #5;        
        clk <= 1; #5; clk <=0; #5;
        clk <= 1; #5; clk <=0; #5;
        clk <= 1; #5; clk <=0; #5;
        clk <= 1; #5; clk <=0; #5;
        clk <= 1; #5; clk <=0; #5;        
        clk <= 1; #5; clk <=0; #5;
        clk <= 1; #5; clk <=0; #5;
        clk <= 1; #5; clk <=0; #5;
        $finish;
    end



initial begin // Response monitor
    $monitor ("t = %3d, clk = %b, reset = %b, WriteData = %b, DataAdr = %b, MemWrite = %b", $time, clk, reset, WriteData, DataAdr, MemWrite);
end


endmodule

single core/XRISC_single_tb.vcd
$date
	Wed Jan 25 00:57:10 2023
$end
$version
	Icarus Verilog
$end
$timescale
	1ps
$end
$scope module XRISC_single_tb $end
$var wire 32 ! WriteData [31:0] $end
$var wire 1 " MemWrite $end
$var wire 32 # DataAdr [31:0] $end
$var reg 1 $ clk $end
$var reg 1 % reset $end
$scope module dut $end
$var wire 1 & Memwrite $end
$var wire 1 $ clk $end
$var wire 1 % reset $end
$var wire 32 ' WriteData [31:0] $end
$var wire 32 ( ReadData [31:0] $end
$var wire 32 ) PC [31:0] $end
$var wire 1 " MemWrite $end
$var wire 32 * Instr [31:0] $end
$var wire 32 + DataAdr [31:0] $end
$scope module XRISC $end
$var wire 1 $ clk $end
$var wire 1 % reset $end
$var wire 1 , Zero $end
$var wire 32 - WriteData [31:0] $end
$var wire 2 . ResultSrc [1:0] $end
$var wire 1 / RegWrite $end
$var wire 32 0 ReadData [31:0] $end
$var wire 1 1 PCSrc $end
$var wire 32 2 PC [31:0] $end
$var wire 1 " MemWrite $end
$var wire 1 3 Jump $end
$var wire 32 4 Instr [31:0] $end
$var wire 2 5 ImmSrc [1:0] $end
$var wire 1 6 ALUSrc $end
$var wire 32 7 ALUResult [31:0] $end
$var wire 4 8 ALUControl [3:0] $end
$scope module c $end
$var wire 1 1 PCSrc $end
$var wire 3 9 funct3 [2:0] $end
$var wire 7 : funct7 [6:0] $end
$var wire 7 ; op [6:0] $end
$var wire 1 , Zero $end
$var wire 2 < ResultSrc [1:0] $end
$var wire 1 / RegWrite $end
$var wire 1 " MemWrite $end
$var wire 1 3 Jump $end
$var wire 2 = ImmSrc [1:0] $end
$var wire 1 > Branch $end
$var wire 1 6 ALUSrc $end
$var wire 2 ? ALUOp [1:0] $end
$var wire 4 @ ALUControl [3:0] $end
$scope module ad $end
$var wire 3 A funct3 [2:0] $end
$var wire 7 B funct7 [6:0] $end
$var wire 1 C opb5 $end
$var wire 2 D ALUOp [1:0] $end
$var reg 4 E ALUControl [3:0] $end
$upscope $end
$scope module md $end
$var wire 7 F op [6:0] $end
$var wire 2 G ResultSrc [1:0] $end
$var wire 1 / RegWrite $end
$var wire 1 " MemWrite $end
$var wire 1 3 Jump $end
$var wire 2 H ImmSrc [1:0] $end
$var wire 1 > Branch $end
$var wire 1 6 ALUSrc $end
$var wire 2 I ALUOp [1:0] $end
$var reg 11 J controls [10:0] $end
$upscope $end
$upscope $end
$scope module dp $end
$var wire 4 K ALUControl [3:0] $end
$var wire 1 6 ALUSrc $end
$var wire 2 L ImmSrc [1:0] $end
$var wire 1 1 PCSrc $end
$var wire 1 / RegWrite $end
$var wire 2 M ResultSrc [1:0] $end
$var wire 1 $ clk $end
$var wire 1 % reset $end
$var wire 1 , Zero $end
$var wire 32 N WriteData [31:0] $end
$var wire 32 O SrcB [31:0] $end
$var wire 32 P SrcA [31:0] $end
$var wire 32 Q Result [31:0] $end
$var wire 32 R ReadData [31:0] $end
$var wire 32 S PCTarget [31:0] $end
$var wire 32 T PCPlus4 [31:0] $end
$var wire 32 U PCNext [31:0] $end
$var wire 32 V PC [31:0] $end
$var wire 32 W Instr [31:0] $end
$var wire 32 X ImmExt [31:0] $end
$var wire 32 Y ALUResult [31:0] $end
$scope module alu $end
$var wire 4 Z ALUControl [3:0] $end
$var wire 33 [ tmp [32:0] $end
$var wire 1 , Zero $end
$var wire 32 \ SrcB [31:0] $end
$var wire 32 ] SrcA [31:0] $end
$var wire 1 ^ ALU_Out $end
$var reg 32 _ ALUResult [31:0] $end
$upscope $end
$scope module ext $end
$var wire 2 ` immsrc [1:0] $end
$var wire 25 a instr [31:7] $end
$var reg 32 b immext [31:0] $end
$upscope $end
$scope module pcadd4 $end
$var wire 32 c b [31:0] $end
$var wire 32 d c [31:0] $end
$var wire 32 e a [31:0] $end
$upscope $end
$scope module pcaddbranch $end
$var wire 32 f b [31:0] $end
$var wire 32 g c [31:0] $end
$var wire 32 h a [31:0] $end
$upscope $end
$scope module pcmux $end
$var wire 32 i d0 [31:0] $end
$var wire 32 j d1 [31:0] $end
$var wire 1 1 s $end
$var wire 32 k y [31:0] $end
$upscope $end
$scope module pcreg $end
$var wire 1 $ clk $end
$var wire 32 l d [31:0] $end
$var wire 1 % reset $end
$var reg 32 m q [31:0] $end
$upscope $end
$scope module resultmux $end
$var wire 32 n d0 [31:0] $end
$var wire 32 o d2 [31:0] $end
$var wire 2 p s [1:0] $end
$var wire 32 q y [31:0] $end
$var wire 32 r d1 [31:0] $end
$upscope $end
$scope module rf $end
$var wire 5 s A1 [4:0] $end
$var wire 5 t A2 [4:0] $end
$var wire 5 u A3 [4:0] $end
$var wire 32 v WD3 [31:0] $end
$var wire 1 / WE3 $end
$var wire 1 $ clk $end
$var wire 32 w RD2 [31:0] $end
$var wire 32 x RD1 [31:0] $end
$upscope $end
$scope module srcbmux $end
$var wire 32 y d0 [31:0] $end
$var wire 32 z d1 [31:0] $end
$var wire 1 6 s $end
$var wire 32 { y [31:0] $end
$upscope $end
$upscope $end
$upscope $end
$scope module dmem $end
$var wire 32 | a [31:0] $end
$var wire 1 $ clk $end
$var wire 32 } rd [31:0] $end
$var wire 32 ~ wd [31:0] $end
$var wire 1 & we $end
$upscope $end
$scope module imem $end
$var wire 32 !" a [31:0] $end
$var wire 32 "" rd [31:0] $end
$upscope $end
$upscope $end
$upscope $end
$scope module resettable_ff_enable $end
$var wire 1 #" clk $end
$var wire 32 $" d [31:0] $end
$var wire 1 %" en $end
$var wire 1 &" reset $end
$var reg 32 '" q [31:0] $end
$upscope $end
$enddefinitions $end
#0
$dumpvars
bx '"
z&"
z%"
bz $"
z#"
b10100000000000100010011 ""
b0 !"
bx ~
bx }
b101 |
b101 {
b101 z
bx y
b0 x
bx w
b101 v
b10 u
b101 t
b0 s
bx r
b101 q
b0 p
b1 o
b101 n
b0 m
b1 l
b1 k
b101 j
b1 i
b0 h
b101 g
b101 f
b0 e
b1 d
b1 c
b101 b
b1010000000000010 a
b0 `
b101 _
1^
b0 ]
b101 \
b101 [
b0 Z
b101 Y
b101 X
b10100000000000100010011 W
b0 V
b1 U
b1 T
b101 S
bx R
b101 Q
b0 P
b101 O
bx N
b0 M
b0 L
b0 K
b10010000100 J
b10 I
b0 H
b0 G
b10011 F
b0 E
b10 D
0C
b0 B
b0 A
b0 @
b10 ?
0>
b0 =
b0 <
b10011 ;
b0 :
b0 9
b0 8
b101 7
16
b0 5
b10100000000000100010011 4
03
b0 2
01
bx 0
1/
b0 .
bx -
0,
b101 +
b10100000000000100010011 *
b0 )
bx (
bx '
z&
1%
1$
b101 #
0"
bx !
$end
#5
0$
#10
1$
#15
0$
#20
1$
#22
0%
#25
0$
#30
b1100 Q
b1100 q
b1100 v
0^
b1100 #
b1100 +
b1100 7
b1100 Y
b1100 _
b1100 n
b1100 |
b1100 [
b1100 O
b1100 \
b1100 {
b1100 X
b1100 b
b1100 f
b1100 z
b11000000000000011 a
b11 u
b1100 t
b10 U
b10 k
b10 l
b110000000000000110010011 *
b110000000000000110010011 4
b110000000000000110010011 W
b110000000000000110010011 ""
b1101 S
b1101 g
b1101 j
b10 T
b10 d
b10 i
b10 o
b1 )
b1 2
b1 V
b1 e
b1 h
b1 m
b1 !"
1$
#35
0$
#40
1^
b11 Q
b11 q
b11 v
b11111111111111111111111111110111 O
b11111111111111111111111111110111 \
b11111111111111111111111111110111 {
b11 #
b11 +
b11 7
b11 Y
b11 _
b11 n
b11 |
b11111111111111111111111111110111 X
b11111111111111111111111111110111 b
b11111111111111111111111111110111 f
b11111111111111111111111111110111 z
b100000000000000000000000000000011 [
b1100 P
b1100 ]
b1100 x
b1111111101110001100000111 a
b111 u
b10111 t
b11 s
b1111111 :
b1111111 B
b11 U
b11 k
b11 l
b11111111011100011000001110010011 *
b11111111011100011000001110010011 4
b11111111011100011000001110010011 W
b11111111011100011000001110010011 ""
b11111111111111111111111111111001 S
b11111111111111111111111111111001 g
b11111111111111111111111111111001 j
b11 T
b11 d
b11 i
b11 o
b10 )
b10 2
b10 V
b10 e
b10 h
b10 m
b10 !"
1$
#45
0$
#50
b111 Q
b111 q
b111 v
b101 O
b101 \
b101 {
b111 #
b111 +
b111 7
b111 Y
b111 _
b111 n
b111 |
bx 5
bx =
bx H
bx L
bx `
06
bx X
bx b
bx f
bx z
b101 !
b101 '
b101 -
b101 N
b101 w
b101 y
b101 ~
b1000 [
b11 P
b11 ]
b11 x
b11 8
b11 @
b11 E
b11 K
b11 Z
1C
b1xx00000100 J
b100011111000100 a
b100 u
b10 t
b111 s
b0 :
b0 B
b110 9
b110 A
b110011 ;
b110011 F
b100 U
b100 k
b100 l
b1000111110001000110011 *
b1000111110001000110011 4
b1000111110001000110011 W
b1000111110001000110011 ""
bx S
bx g
bx j
b100 T
b100 d
b100 i
b100 o
b11 )
b11 2
b11 V
b11 e
b11 h
b11 m
b11 !"
1$
#55
0$
#60
b100 Q
b100 q
b100 v
0^
b111 O
b111 \
b111 {
b100 #
b100 +
b100 7
b100 Y
b100 _
b100 n
b100 |
b111 !
b111 '
b111 -
b111 N
b111 w
b111 y
b111 ~
b10011 [
b1100 P
b1100 ]
b1100 x
b10 8
b10 @
b10 E
b10 K
b10 Z
b1000001111100101 a
b101 u
b100 t
b11 s
b111 9
b111 A
b101 U
b101 k
b101 l
b10000011111001010110011 *
b10000011111001010110011 4
b10000011111001010110011 W
b10000011111001010110011 ""
b101 T
b101 d
b101 i
b101 o
b100 )
b100 2
b100 V
b100 e
b100 h
b100 m
b100 !"
1$
#65
0$
#70
b1011 Q
b1011 q
b1011 v
1^
b1011 #
b1011 +
b1011 7
b1011 Y
b1011 _
b1011 n
b1011 |
b1011 [
b100 P
b100 ]
b100 x
b0 8
b0 @
b0 E
b0 K
b0 Z
b1000010100000101 a
b101 s
b0 9
b0 A
b110 U
b110 k
b110 l
b10000101000001010110011 *
b10000101000001010110011 4
b10000101000001010110011 W
b10000101000001010110011 ""
b110 T
b110 d
b110 i
b110 o
b101 )
b101 2
b101 V
b101 e
b101 h
b101 m
b101 !"
1$
#75
0$
#80
b110110 S
b110110 g
b110110 j
b110000 X
b110000 b
b110000 f
b110000 z
b1000 Q
b1000 q
b1000 v
b11 O
b11 \
b11 {
0/
b10 5
b10 =
b10 H
b10 L
b10 `
1>
b1 ?
b1 D
b1 I
0^
b11 !
b11 '
b11 -
b11 N
b11 w
b11 y
b11 ~
b1000001010 J
b1 8
b1 @
b1 E
b1 K
b1 Z
b1000 #
b1000 +
b1000 7
b1000 Y
b1000 _
b1000 n
b1000 |
b1001110010100010000 a
b10000 u
b111 t
b1 :
b1 B
b1100011 ;
b1100011 F
b111 U
b111 k
b111 l
b1110 [
b1011 P
b1011 ]
b1011 x
b10011100101000100001100011 *
b10011100101000100001100011 4
b10011100101000100001100011 W
b10011100101000100001100011 ""
b111 T
b111 d
b111 i
b111 o
b110 )
b110 2
b110 V
b110 e
b110 h
b110 m
b110 !"
1$
#85
0$
#90
b1001 Q
b1001 q
b1001 v
1^
b111 O
b111 \
b111 {
b101 8
b101 @
b101 E
b101 K
b101 Z
b1001 #
b1001 +
b1001 7
b1001 Y
b1001 _
b1001 n
b1001 |
1/
bx 5
bx =
bx H
bx L
bx `
0>
b10 ?
b10 D
b10 I
bx X
bx b
bx f
bx z
b111 !
b111 '
b111 -
b111 N
b111 w
b111 y
b111 ~
b10011 [
b1100 P
b1100 ]
b1100 x
b1xx00000100 J
b1000001101000100 a
b100 u
b100 t
b11 s
b0 :
b0 B
b10 9
b10 A
b110011 ;
b110011 F
b1000 U
b1000 k
b1000 l
b10000011010001000110011 *
b10000011010001000110011 4
b10000011010001000110011 W
b10000011010001000110011 ""
bx S
bx g
bx j
b1000 T
b1000 d
b1000 i
b1000 o
b111 )
b111 2
b111 V
b111 e
b111 h
b111 m
b111 !"
1$
#95
0$
#100
b1001 Q
b1001 q
b1001 v
b10000 S
b10000 g
b10000 j
b1000 X
b1000 b
b1000 f
b1000 z
1^
0/
b10 5
b10 =
b10 H
b10 L
b10 `
1>
b1 ?
b1 D
b1 I
b1001 #
b1001 +
b1001 7
b1001 Y
b1001 _
b1001 n
b1001 |
b1001 P
b1001 ]
b1001 x
b1 8
b1 @
b1 E
b1 K
b1 Z
b1000001010 J
b1001 [
b0 O
b0 \
b0 {
b10000001000 a
b1000 u
b0 t
b100 s
b0 9
b0 A
b1100011 ;
b1100011 F
b1001 U
b1001 k
b1001 l
b0 !
b0 '
b0 -
b0 N
b0 w
b0 y
b0 ~
b100000010001100011 *
b100000010001100011 4
b100000010001100011 W
b100000010001100011 ""
b1001 T
b1001 d
b1001 i
b1001 o
b1000 )
b1000 2
b1000 V
b1000 e
b1000 h
b1000 m
b1000 !"
1$
#105
0$
#110
b0 Q
b0 q
b0 v
0^
b0 O
b0 \
b0 {
b0 8
b0 @
b0 E
b0 K
b0 Z
1,
b0 #
b0 +
b0 7
b0 Y
b0 _
b0 n
b0 |
1/
b0 5
b0 =
b0 H
b0 L
b0 `
16
0>
b10 ?
b10 D
b10 I
b0 X
b0 b
b0 f
b0 z
b0 [
b0 P
b0 ]
b0 x
0C
b10010000100 J
b101 a
b101 u
b0 s
b10011 ;
b10011 F
b1010 U
b1010 k
b1010 l
b1010010011 *
b1010010011 4
b1010010011 W
b1010010011 ""
b1001 S
b1001 g
b1001 j
b1010 T
b1010 d
b1010 i
b1010 o
b1001 )
b1001 2
b1001 V
b1001 e
b1001 h
b1001 m
b1001 !"
1$
#115
0$
#120
b101 O
b101 \
b101 {
bx 5
bx =
bx H
bx L
bx `
06
bx X
bx b
bx f
bx z
b101 !
b101 '
b101 -
b101 N
b101 w
b101 y
b101 ~
b1000 [
b11 P
b11 ]
b11 x
b101 8
b101 @
b101 E
b101 K
b101 Z
1C
b1xx00000100 J
b100011101000100 a
b100 u
b10 t
b111 s
b10 9
b10 A
b110011 ;
b110011 F
b1011 U
b1011 k
b1011 l
b1000111010001000110011 *
b1000111010001000110011 4
b1000111010001000110011 W
b1000111010001000110011 ""
bx S
bx g
bx j
b1011 T
b1011 d
b1011 i
b1011 o
b1010 )
b1010 2
b1010 V
b1010 e
b1010 h
b1010 m
b1010 !"
1$
#125
0$
#130
b0 Q
b0 q
b0 v
0^
b0 O
b0 \
b0 {
1,
b0 #
b0 +
b0 7
b0 Y
b0 _
b0 n
b0 |
b0 !
b0 '
b0 -
b0 N
b0 w
b0 y
b0 ~
b0 [
b0 P
b0 ]
b0 x
b0 8
b0 @
b0 E
b0 K
b0 Z
b1010010000000111 a
b111 u
b101 t
b100 s
b0 9
b0 A
b1100 U
b1100 k
b1100 l
b10100100000001110110011 *
b10100100000001110110011 4
b10100100000001110110011 W
b10100100000001110110011 ""
b1100 T
b1100 d
b1100 i
b1100 o
b1011 )
b1011 2
b1011 V
b1011 e
b1011 h
b1011 m
b1011 !"
1$
#135
0$
#140
b11111111111111111111111111111011 Q
b11111111111111111111111111111011 q
b11111111111111111111111111111011 v
1^
0,
b11111111111111111111111111111011 #
b11111111111111111111111111111011 +
b11111111111111111111111111111011 7
b11111111111111111111111111111011 Y
b11111111111111111111111111111011 _
b11111111111111111111111111111011 n
b11111111111111111111111111111011 |
b101 [
b101 O
b101 \
b101 {
b101 !
b101 '
b101 -
b101 N
b101 w
b101 y
b101 ~
b1 8
b1 @
b1 E
b1 K
b1 Z
b100000000100011100000111 a
b10 t
b111 s
b100000 :
b100000 B
b1101 U
b1101 k
b1101 l
b1000000001000111000001110110011 *
b1000000001000111000001110110011 4
b1000000001000111000001110110011 W
b1000000001000111000001110110011 ""
b1101 T
b1101 d
b1101 i
b1101 o
b1100 )
b1100 2
b1100 V
b1100 e
b1100 h
b1100 m
b1100 !"
1$
#145
0$
#150
0,
b1100001 S
b1100001 g
b1100001 j
b1010100 X
b1010100 b
b1010100 f
b1010100 z
b1100000 Q
b1100000 q
b1100000 v
b1010100 O
b1010100 \
b1010100 {
0/
b1 5
b1 =
b1 H
b1 L
b1 `
16
1"
b0 ?
b0 D
b0 I
0^
b11111111111111111111111111111011 !
b11111111111111111111111111111011 '
b11111111111111111111111111111011 -
b11111111111111111111111111111011 N
b11111111111111111111111111111011 w
b11111111111111111111111111111011 y
b11111111111111111111111111111011 ~
b111000000 J
b0 8
b0 @
b0 E
b0 K
b0 Z
b1100000 #
b1100000 +
b1100000 7
b1100000 Y
b1100000 _
b1100000 n
b1100000 |
b10001110001101010100 a
b10100 u
b111 t
b11 s
b10 :
b10 B
b10 9
b10 A
b100011 ;
b100011 F
b1110 U
b1110 k
b1110 l
b1100000 [
b1100 P
b1100 ]
b1100 x
b100011100011010101000100011 *
b100011100011010101000100011 4
b100011100011010101000100011 W
b100011100011010101000100011 ""
b1110 T
b1110 d
b1110 i
b1110 o
b1101 )
b1101 2
b1101 V
b1101 e
b1101 h
b1101 m
b1101 !"
1$
#155
0$
#160
bx Q
bx q
bx v
b110 O
b110 \
b110 {
b110 #
b110 +
b110 7
b110 Y
b110 _
b110 n
b110 |
1/
b0 5
b0 =
b0 H
b0 L
b0 `
0"
b1 .
b1 <
b1 G
b1 M
b1 p
b110 X
b110 b
b110 f
b110 z
bx !
bx '
bx -
bx N
bx w
bx y
bx ~
b110 [
b0 P
b0 ]
b0 x
0C
b10010010000 J
b1100000001000010 a
b10 u
b110 t
b0 s
b0 :
b0 B
b11 ;
b11 F
b1111 U
b1111 k
b1111 l
b11000000010000100000011 *
b11000000010000100000011 4
b11000000010000100000011 W
b11000000010000100000011 ""
b10100 S
b10100 g
b10100 j
b1111 T
b1111 d
b1111 i
b1111 o
b1110 )
b1110 2
b1110 V
b1110 e
b1110 h
b1110 m
b1110 !"
1$
#165
0$
#170
x^
b0 O
b0 \
b0 {
x,
bx #
bx +
bx 7
bx Y
bx _
bx n
bx |
bx 5
bx =
bx H
bx L
bx `
06
b0 .
b0 <
b0 G
b0 M
b0 p
b10 ?
b10 D
b10 I
bx X
bx b
bx f
bx z
b0 !
b0 '
b0 -
b0 N
b0 w
b0 y
b0 ~
bx [
bx P
bx ]
bx x
1C
b1xx00000100 J
b1010001000001001 a
b1001 u
b101 t
b10 s
b0 9
b0 A
b110011 ;
b110011 F
b10000 U
b10000 k
b10000 l
b10100010000010010110011 *
b10100010000010010110011 4
b10100010000010010110011 W
b10100010000010010110011 ""
bx S
bx g
bx j
b10000 T
b10000 d
b10000 i
b10000 o
b1111 )
b1111 2
b1111 V
b1111 e
b1111 h
b1111 m
b1111 !"
1$
#175
0$
#180
bx O
bx \
bx {
bx !
bx '
bx -
bx N
bx w
bx y
bx ~
b1001 8
b1001 @
b1001 E
b1001 K
b1001 Z
b1000100100100001010 a
b1010 u
b10 t
b1001 s
b1 :
b1 B
b10001 U
b10001 k
b10001 l
b10001001001000010100110011 *
b10001001001000010100110011 4
b10001001001000010100110011 W
b10001001001000010100110011 ""
b10001 T
b10001 d
b10001 i
b10001 o
b10000 )
b10000 2
b10000 V
b10000 e
b10000 h
b10000 m
b10000 !"
1$
#185
0$
