single core/XRISC_single.sv
//Top-level Module
module top(input         clk, reset, 
           output [31:0] WriteData, DataAdr, 
           output        MemWrite);

  logic [31:0] PC, Instr, ReadData;
  
  // instantiate processor and memories
  XRISC_single XRISC(clk, reset, PC, Instr, MemWrite, DataAdr, WriteData, ReadData);
  imem imem(PC, Instr);
  dmem dmem(clk, MemWrite, DataAdr, WriteData, ReadData);
endmodule

//Single-cycle RISC-V processor
module XRISC_single(input  logic        clk,reset,
                    output logic [31:0] PC,
                    input  logic [31:0] Instr,
                    output logic        MemWrite,
                    output logic [31:0] ALUResult,WriteData,
                    input  logic [31:0] ReadData);

    logic ALUSrc, RegWrite, Jump, Zero;
    logic [1:0] ResultSrc, ImmSrc;
    logic [3:0] ALUControl;

    controller c(Instr[6:0],Instr[14:12],Instr[31:25], Zero, ResultSrc, MemWrite, PCSrc, ALUSrc, RegWrite, Jump, ImmSrc, ALUControl);

    datapath dp(clk, reset, ResultSrc, PCSrc, ALUSrc, RegWrite, ImmSrc, ALUControl, Zero, PC, Instr, ALUResult, WriteData, ReadData);

endmodule

//Controller
module controller(  input logic [6:0] op,
                    input logic [2:0] funct3,
                    input logic [6:0] funct7,
                    input logic       Zero,
                    output logic [1:0] ResultSrc,
                    output logic       MemWrite,
                    output logic       PCSrc, ALUSrc,
                    output logic       RegWrite, Jump,
                    output logic [1:0] ImmSrc,
                    output logic [3:0] ALUControl);
    logic [1:0] ALUOp;
    logic Branch;

    Main_decoder md(op, ResultSrc,MemWrite, Branch, ALUSrc, RegWrite, Jump, ImmSrc, ALUOp);
    ALU_decoder ad(ALUOp, funct3, op, funct7, ALUControl);

    assign PCSrc = (Branch & Zero) | Jump;
endmodule

//Main decoder
module Main_decoder(input logic [6:0] op,
                    output logic [1:0] ResultSrc,
                    output logic       MemWrite,
                    output logic       Branch, ALUSrc,
                    output logic       RegWrite, Jump,
                    output logic [1:0] ImmSrc,
                    output logic [1:0] ALUOp);
    logic [10:0] controls;

    assign {RegWrite, ImmSrc, ALUSrc, MemWrite, ResultSrc, Branch, ALUOp, Jump} = controls;

    always_comb  
    
        case(op)
        //RegWrite_ImmSrc_ALUSrc_MemWrite_ResultSrc_Branch_ALUOp_Jump
        7'b0000011: controls = 11'b1_00_1_0_01_0_00_0; //lw
        7'b0100011: controls = 11'b0_01_1_1_00_0_00_0; //sw
        7'b0110011: controls = 11'b1_xx_0_0_00_0_10_0; //R-type
        7'b1100011: controls = 11'b0_10_0_0_00_1_01_0; //beq
        7'b0010011: controls = 11'b1_00_1_0_00_0_10_0; //I-type ALU
        7'b1101111: controls = 11'b1_11_0_0_10_0_00_1; //jal
        default:    controls = 11'bx_xx_x_x_xx_x_xx_x; //???

        
        endcase
endmodule

//ALU decoder
module ALU_decoder(input logic  [1:0] ALUOp,
                    input logic [2:0] funct3,
                    input logic [6:0] op,
                    input logic [6:0] funct7,                    
                    output logic [3:0] ALUControl);
    
   always_comb

        case(ALUOp)
            2'b00:                      ALUControl = 4'b0000; // performs addition;
            2'b01:                      ALUControl = 4'b0001; // performs subtraction;
    
            default: case(funct3)
                    3'b000: 
                        case(op)
                            7'b0010011:
                                case(funct3)
                                3'b000:             ALUControl = 4'b0000; //addi;
                                endcase
                            7'b110011:
                                case(funct7)
                                7'b0000000:         ALUControl = 4'b0000; // add;
                                7'b0000001:         ALUControl = 4'b1001; // multiply;
                                7'b0100000:         ALUControl = 4'b0001; // R type subtraction;
                                default:			ALUControl = 4'bx;
                                endcase
                        endcase
                    3'b010:                 
                        

                                  ALUControl = 4'b0101; // slti, set less than;

                        

                    3'b110:                 ALUControl = 4'b0011; // or,ori;
                    3'b111:                 ALUControl = 4'b0010; // and,andi;
                    3'b100:                 ALUControl = 4'b0100; // divide(signed)
                    3'b101: if (funct7 == 7'b0100000)        
                                            ALUControl = 4'b0110; // shift right arithmetic
                            else
                                            ALUControl = 4'b0111; // shift right logical
                    3'b001:                 ALUControl = 4'b1000; // shift left logical
                    default:                ALUControl = 4'bxxxx; // ???
                        
            endcase
        endcase
endmodule

//Datapath
module datapath(input  logic        clk,reset,
                input  logic [1:0]  ResultSrc,
                input  logic        PCSrc,ALUSrc,
                input  logic        RegWrite,
                input  logic [1:0]  ImmSrc,
                input  logic [3:0]  ALUControl,
                output logic        Zero,
                output logic [31:0] PC,
                input  logic [31:0] Instr,
                output logic [31:0] ALUResult, WriteData,
                input  logic [31:0] ReadData);
    logic [31:0] PCNext, PCPlus4, PCTarget;
    logic [31:0] ImmExt;
    logic [31:0] SrcA, SrcB;
    logic [31:0] Result;

    //next PC logic
    resettable_ff #(32) pcreg(clk, reset, PCNext, PC);
    adder       pcadd4(PC,32'd4, PCPlus4);
    adder       pcaddbranch(PC, ImmExt, PCTarget);
    mux2 #(32)  pcmux(PCPlus4, PCTarget, PCSrc, PCNext);

    //register file logic
    regfile     rf(clk, RegWrite, Instr[19:15], Instr[24:20], Instr[11:7], Result, SrcA, WriteData);
    extendunit      ext(Instr[31:7], ImmSrc, ImmExt);

    //ALU logic
    mux2 #(32)  srcbmux(WriteData,ImmExt, ALUSrc, SrcB);
    alu         alu(SrcA, SrcB, ALUControl, ALUResult, Zero);
    mux3 #(32)  resultmux(ALUResult, ReadData, PCPlus4, ResultSrc, Result);

endmodule

module alu(input logic          [31:0] SrcA,SrcB,  // ALU 32-bit Inputs                 
           input logic          [3:0] ALUControl,// ALU Control signal from ALU decoder
           output logic         [31:0] ALUResult, // ALU 32-bit Output
           output logic         Zero); // Zero Flag
   
    logic [32:0] ALU_Result;
    wire [32:0] tmp;
    assign ALU_Out = ALUResult; // ALU out
    assign tmp = {1'b0,SrcA} + {1'b0,SrcB};
    assign Zero = (ALUResult == 32'b0); // Zero flag
    //assign CarryOut = tmp[32]; // Carryout flag
    
    always_comb
        case(ALUControl)
            4'b0000: // Addition
               ALUResult = SrcA + SrcB ; 
            4'b0001: // Subtraction
               ALUResult = SrcA - SrcB ;
            4'b1001: // Multiplication
               ALUResult = SrcA * SrcB;
            4'b0100: // Division
               ALUResult = SrcA / SrcB;
            4'b1000: // shift left logical
               ALUResult = SrcA << SrcB;
            4'b0111: // Logical shift right
               ALUResult = SrcA >> SrcB;
            4'b0010: //  and 
               ALUResult = SrcA & SrcB;
            4'b0011: //  or
               ALUResult = SrcA | SrcB;
            4'b0110: // shift right arithmetic
               ALUResult = SrcA >>> SrcB;       
            4'b0101: // set less than
                if (SrcA < SrcB)
                ALUResult = 32'b1;
                else
                ALUResult = 32'b0;
			default:
				ALUResult = 32'bx;

        endcase
endmodule 

module adder(input logic  [31:0] a,
             input logic  [31:0] b,
             output logic  [31:0] c);
  //logic [32:0] y_test;
    assign c = a + b;
                                
endmodule

module extendunit(input logic [31:7] instr,
                  input logic [1:0]  immsrc,
                  output logic [31:0] immext);
    always@*
        case(immsrc)
            // I type
            2'b00: immext = {{20{instr[31]}}, {instr[31:20]}};
            // S type
            2'b01: immext = {{20{instr[31]}}, {instr[31:25]}, {instr[11:7]}};
            // B type
            2'b10: immext = {{20{instr[31]}}, {instr[7]}, { instr[30:25]}, {instr[11:8]}, 1'b0};
            // J type
            2'b11: immext = {{12{instr[31]}}, {instr[19:12]}, { instr[20]}, {instr[30:21]}, 1'b0};
            default: immext = 32'bx;
        endcase
endmodule

module resettable_ff_enable #(parameter WIDTH = 32)
                (input logic            clk, reset, en,
                 input logic [WIDTH-1:0]d,
                 output logic [WIDTH-1:0]q);
always_ff@(posedge clk, posedge reset)
    if (reset) q <= 0;
    else if (en) q <= d;
endmodule

module resettable_ff #(parameter WIDTH = 32)
                (input logic            clk, reset,
                 input logic [WIDTH-1:0]d,
                 output logic [WIDTH-1:0]q);
always_ff@(posedge clk, posedge reset)
    if (reset)  q <= 0;
    else        q <= d;
endmodule

module mux3 #(parameter WIDTH = 8)
            (input logic [WIDTH-1:0] d0, d1, d2,
            input logic  [1:0]       s,
            output logic [WIDTH-1:0] y);

assign y = s[1] ? d2 : (s[0] ? d1 : d0);
endmodule

module mux2 #(parameter WIDTH = 8)
            (input logic [WIDTH-1:0] d0, d1, 
            input logic              s,
            output logic [WIDTH-1:0] y);

assign y = s ? d1 : d0;
endmodule

//data memory
module dmem(input  logic            clk, we,
            input  logic    [31:0] a, wd,
            output logic    [31:0] rd);

  logic  [31:0] RAM[0:100];
 
  assign rd = RAM[a]; // word aligned

  always @(posedge clk)
    if (we)
      RAM[a] <= wd;
endmodule

//instruction memory
module imem(input  logic    [31:0] a,
            output logic    [31:0] rd);

  logic[7:0]RAM[0:300];
  

  initial
    begin
      $readmemh("riscvtest2.txt",RAM);
    end
 
  assign rd = {RAM[a],RAM[a+1],RAM[a+2],RAM[a+3]}; // word aligned
endmodule

module regfile(input logic      clk, 
               input logic           WE3, 
               input logic [4:0]     A1, A2, A3, 
               input logic [31:0]    WD3, 
               output logic [31:0]    RD1, RD2);
    reg [31:0] rf[0:100];
    always @(posedge clk)
        if (WE3) rf[A3] <= WD3;	

    assign RD1 = (A1 != 0) ? rf[A1] : 0;
    assign RD2 = (A2 != 0) ? rf[A2] : 0;
endmodule

single core/XRISC_single_tb.sv
`timescale 1ps/1ps
`include "XRISC_single.sv"

module XRISC_single_tb();

    logic           clk;
    logic           reset;
    logic   [31:0]  WriteData, DataAdr;
    logic           MemWrite;
    

top dut(clk, reset, WriteData, DataAdr,MemWrite);

//initialize test
initial 
    begin
        reset <= 1;#22; reset <= 0;
    end


initial begin
    $dumpfile("XRISC_single_tb.vcd");
    $dumpvars;
end
    
//generate clock to sequence tests
    always 
    begin        
        clk <= 1; #5; clk <=0; #5;
        clk <= 1; #5; clk <=0; #5;
        clk <= 1; #5; clk <=0; #5;
        clk <= 1; #5; clk <=0; #5;
        clk <= 1; #5; clk <=0; #5;
        clk <= 1; #5; clk <=0; #5;
        clk <= 1; #5; clk <=0; #5;
        clk <= 1; #5; clk <=0; #5;        
        clk <= 1; #5; clk <=0; #5;
        clk <= 1; #5; clk <=0; #5;
        clk <= 1; #5; clk <=0; #5;
        clk <= 1; #5; clk <=0; #5;
        clk <= 1; #5; clk <=0; #5;
        clk <= 1; #5; clk <=0; #5;
        clk <= 1; #5; clk <=0; #5;
        clk <= 1; #5; clk <=0; #5;
        clk <= 1; #5; clk <=0; #5;
        clk <= 1; #5; clk <=0; #5;
        clk <= 1; #5; clk <=0; #5;        
        clk <= 1; #5; clk <=0; #5;
        clk <= 1; #5; clk <=0; #5;
        clk <= 1; #5; clk <=0; #5;
        clk <= 1; #5; clk <=0; #5;
        clk <= 1; #5; clk <=0; #5;
               

        $finish;
    end



initial begin // Response monitor
    $monitor ("t = %3d, clk = %b, reset = %b, WriteData = %b, DataAdr = %b, MemWrite = %b", $time, clk, reset, WriteData, DataAdr, MemWrite);
end


endmodule

single core/XRISC_single_tb.vcd
$date
	Wed Feb 01 22:34:21 2023
$end
$version
	Icarus Verilog
$end
$timescale
	1ps
$end
$scope module XRISC_single_tb $end
$var wire 32 ! WriteData [31:0] $end
$var wire 1 " MemWrite $end
$var wire 32 # DataAdr [31:0] $end
$var reg 1 $ clk $end
$var reg 1 % reset $end
$scope module dut $end
$var wire 1 $ clk $end
$var wire 1 % reset $end
$var wire 32 & WriteData [31:0] $end
$var wire 32 ' ReadData [31:0] $end
$var wire 32 ( PC [31:0] $end
$var wire 1 " MemWrite $end
$var wire 32 ) Instr [31:0] $end
$var wire 32 * DataAdr [31:0] $end
$scope module XRISC $end
$var wire 1 $ clk $end
$var wire 1 % reset $end
$var wire 1 + Zero $end
$var wire 32 , WriteData [31:0] $end
$var wire 2 - ResultSrc [1:0] $end
$var wire 1 . RegWrite $end
$var wire 32 / ReadData [31:0] $end
$var wire 1 0 PCSrc $end
$var wire 32 1 PC [31:0] $end
$var wire 1 " MemWrite $end
$var wire 1 2 Jump $end
$var wire 32 3 Instr [31:0] $end
$var wire 2 4 ImmSrc [1:0] $end
$var wire 1 5 ALUSrc $end
$var wire 32 6 ALUResult [31:0] $end
$var wire 4 7 ALUControl [3:0] $end
$scope module c $end
$var wire 1 0 PCSrc $end
$var wire 3 8 funct3 [2:0] $end
$var wire 7 9 funct7 [6:0] $end
$var wire 7 : op [6:0] $end
$var wire 1 + Zero $end
$var wire 2 ; ResultSrc [1:0] $end
$var wire 1 . RegWrite $end
$var wire 1 " MemWrite $end
$var wire 1 2 Jump $end
$var wire 2 < ImmSrc [1:0] $end
$var wire 1 = Branch $end
$var wire 1 5 ALUSrc $end
$var wire 2 > ALUOp [1:0] $end
$var wire 4 ? ALUControl [3:0] $end
$scope module ad $end
$var wire 3 @ funct3 [2:0] $end
$var wire 7 A funct7 [6:0] $end
$var wire 7 B op [6:0] $end
$var wire 2 C ALUOp [1:0] $end
$var reg 4 D ALUControl [3:0] $end
$upscope $end
$scope module md $end
$var wire 7 E op [6:0] $end
$var wire 2 F ResultSrc [1:0] $end
$var wire 1 . RegWrite $end
$var wire 1 " MemWrite $end
$var wire 1 2 Jump $end
$var wire 2 G ImmSrc [1:0] $end
$var wire 1 = Branch $end
$var wire 1 5 ALUSrc $end
$var wire 2 H ALUOp [1:0] $end
$var reg 11 I controls [10:0] $end
$upscope $end
$upscope $end
$scope module dp $end
$var wire 4 J ALUControl [3:0] $end
$var wire 1 5 ALUSrc $end
$var wire 2 K ImmSrc [1:0] $end
$var wire 1 0 PCSrc $end
$var wire 1 . RegWrite $end
$var wire 2 L ResultSrc [1:0] $end
$var wire 1 $ clk $end
$var wire 1 % reset $end
$var wire 1 + Zero $end
$var wire 32 M WriteData [31:0] $end
$var wire 32 N SrcB [31:0] $end
$var wire 32 O SrcA [31:0] $end
$var wire 32 P Result [31:0] $end
$var wire 32 Q ReadData [31:0] $end
$var wire 32 R PCTarget [31:0] $end
$var wire 32 S PCPlus4 [31:0] $end
$var wire 32 T PCNext [31:0] $end
$var wire 32 U PC [31:0] $end
$var wire 32 V Instr [31:0] $end
$var wire 32 W ImmExt [31:0] $end
$var wire 32 X ALUResult [31:0] $end
$scope module alu $end
$var wire 4 Y ALUControl [3:0] $end
$var wire 33 Z tmp [32:0] $end
$var wire 1 + Zero $end
$var wire 32 [ SrcB [31:0] $end
$var wire 32 \ SrcA [31:0] $end
$var wire 1 ] ALU_Out $end
$var reg 32 ^ ALUResult [31:0] $end
$upscope $end
$scope module ext $end
$var wire 2 _ immsrc [1:0] $end
$var wire 25 ` instr [31:7] $end
$var reg 32 a immext [31:0] $end
$upscope $end
$scope module pcadd4 $end
$var wire 32 b b [31:0] $end
$var wire 32 c c [31:0] $end
$var wire 32 d a [31:0] $end
$upscope $end
$scope module pcaddbranch $end
$var wire 32 e b [31:0] $end
$var wire 32 f c [31:0] $end
$var wire 32 g a [31:0] $end
$upscope $end
$scope module pcmux $end
$var wire 32 h d0 [31:0] $end
$var wire 32 i d1 [31:0] $end
$var wire 1 0 s $end
$var wire 32 j y [31:0] $end
$upscope $end
$scope module pcreg $end
$var wire 1 $ clk $end
$var wire 32 k d [31:0] $end
$var wire 1 % reset $end
$var reg 32 l q [31:0] $end
$upscope $end
$scope module resultmux $end
$var wire 32 m d0 [31:0] $end
$var wire 32 n d2 [31:0] $end
$var wire 2 o s [1:0] $end
$var wire 32 p y [31:0] $end
$var wire 32 q d1 [31:0] $end
$upscope $end
$scope module rf $end
$var wire 5 r A1 [4:0] $end
$var wire 5 s A2 [4:0] $end
$var wire 5 t A3 [4:0] $end
$var wire 32 u WD3 [31:0] $end
$var wire 1 . WE3 $end
$var wire 1 $ clk $end
$var wire 32 v RD2 [31:0] $end
$var wire 32 w RD1 [31:0] $end
$upscope $end
$scope module srcbmux $end
$var wire 32 x d0 [31:0] $end
$var wire 32 y d1 [31:0] $end
$var wire 1 5 s $end
$var wire 32 z y [31:0] $end
$upscope $end
$upscope $end
$upscope $end
$scope module dmem $end
$var wire 32 { a [31:0] $end
$var wire 1 $ clk $end
$var wire 32 | rd [31:0] $end
$var wire 32 } wd [31:0] $end
$var wire 1 " we $end
$upscope $end
$scope module imem $end
$var wire 32 ~ a [31:0] $end
$var wire 32 !" rd [31:0] $end
$upscope $end
$upscope $end
$upscope $end
$scope module resettable_ff_enable $end
$var wire 1 "" clk $end
$var wire 32 #" d [31:0] $end
$var wire 1 $" en $end
$var wire 1 %" reset $end
$var reg 32 &" q [31:0] $end
$upscope $end
$enddefinitions $end
#0
$dumpvars
bx &"
z%"
z$"
bz #"
z""
b10100000000000100010011 !"
b0 ~
bx }
bx |
b101 {
b101 z
b101 y
bx x
b0 w
bx v
b101 u
b10 t
b101 s
b0 r
bx q
b101 p
b0 o
b100 n
b101 m
b0 l
b100 k
b100 j
b101 i
b100 h
b0 g
b101 f
b101 e
b0 d
b100 c
b100 b
b101 a
b1010000000000010 `
b0 _
b101 ^
1]
b0 \
b101 [
b101 Z
b0 Y
b101 X
b101 W
b10100000000000100010011 V
b0 U
b100 T
b100 S
b101 R
bx Q
b101 P
b0 O
b101 N
bx M
b0 L
b0 K
b0 J
b10010000100 I
b10 H
b0 G
b0 F
b10011 E
b0 D
b10 C
b10011 B
b0 A
b0 @
b0 ?
b10 >
0=
b0 <
b0 ;
b10011 :
b0 9
b0 8
b0 7
b101 6
15
b0 4
b10100000000000100010011 3
02
b0 1
00
bx /
1.
b0 -
bx ,
0+
b101 *
b10100000000000100010011 )
b0 (
bx '
bx &
1%
1$
b101 #
0"
bx !
$end
#5
0$
#10
1$
#15
0$
#20
1$
#22
0%
#25
0$
#30
b1100 P
b1100 p
b1100 u
0]
b1100 #
b1100 *
b1100 6
b1100 X
b1100 ^
b1100 m
b1100 {
b1100 Z
b1100 N
b1100 [
b1100 z
b1100 W
b1100 a
b1100 e
b1100 y
b1100 s
b11000000000000011 `
b11 t
b1000 T
b1000 j
b1000 k
b110000000000000110010011 )
b110000000000000110010011 3
b110000000000000110010011 V
b110000000000000110010011 !"
b10000 R
b10000 f
b10000 i
b1000 S
b1000 c
b1000 h
b1000 n
b100 (
b100 1
b100 U
b100 d
b100 g
b100 l
b100 ~
1$
#35
0$
#40
1]
b11 P
b11 p
b11 u
b11111111111111111111111111110111 N
b11111111111111111111111111110111 [
b11111111111111111111111111110111 z
b11 #
b11 *
b11 6
b11 X
b11 ^
b11 m
b11 {
b11111111111111111111111111110111 W
b11111111111111111111111111110111 a
b11111111111111111111111111110111 e
b11111111111111111111111111110111 y
b100000000000000000000000000000011 Z
b1100 O
b1100 \
b1100 w
b1111111 9
b1111111 A
b10111 s
b1111111101110001100000111 `
b111 t
b11 r
b1100 T
b1100 j
b1100 k
b11111111011100011000001110010011 )
b11111111011100011000001110010011 3
b11111111011100011000001110010011 V
b11111111011100011000001110010011 !"
b11111111111111111111111111111111 R
b11111111111111111111111111111111 f
b11111111111111111111111111111111 i
b1100 S
b1100 c
b1100 h
b1100 n
b1000 (
b1000 1
b1000 U
b1000 d
b1000 g
b1000 l
b1000 ~
1$
#45
0$
#50
b111 P
b111 p
b111 u
b101 N
b101 [
b101 z
b111 #
b111 *
b111 6
b111 X
b111 ^
b111 m
b111 {
bx 4
bx <
bx G
bx K
bx _
05
b101 !
b101 &
b101 ,
b101 M
b101 v
b101 x
b101 }
b1000 Z
b11 O
b11 \
b11 w
bx W
bx a
bx e
bx y
b11 7
b11 ?
b11 D
b11 J
b11 Y
b1xx00000100 I
b0 9
b0 A
b10 s
b111 r
b110 8
b110 @
b100011111000100 `
b100 t
b110011 :
b110011 B
b110011 E
b10000 T
b10000 j
b10000 k
b1000111110001000110011 )
b1000111110001000110011 3
b1000111110001000110011 V
b1000111110001000110011 !"
bx R
bx f
bx i
b10000 S
b10000 c
b10000 h
b10000 n
b1100 (
b1100 1
b1100 U
b1100 d
b1100 g
b1100 l
b1100 ~
1$
#55
0$
#60
b100 P
b100 p
b100 u
0]
b111 N
b111 [
b111 z
b100 #
b100 *
b100 6
b100 X
b100 ^
b100 m
b100 {
b111 !
b111 &
b111 ,
b111 M
b111 v
b111 x
b111 }
b10011 Z
b1100 O
b1100 \
b1100 w
b10 7
b10 ?
b10 D
b10 J
b10 Y
b100 s
b11 r
b111 8
b111 @
b1000001111100101 `
b101 t
b10100 T
b10100 j
b10100 k
b10000011111001010110011 )
b10000011111001010110011 3
b10000011111001010110011 V
b10000011111001010110011 !"
b10100 S
b10100 c
b10100 h
b10100 n
b10000 (
b10000 1
b10000 U
b10000 d
b10000 g
b10000 l
b10000 ~
1$
#65
0$
#70
b1011 P
b1011 p
b1011 u
1]
b1011 #
b1011 *
b1011 6
b1011 X
b1011 ^
b1011 m
b1011 {
b1011 Z
b100 O
b100 \
b100 w
b0 7
b0 ?
b0 D
b0 J
b0 Y
b101 r
b1000010100000101 `
b0 8
b0 @
b11000 T
b11000 j
b11000 k
b10000101000001010110011 )
b10000101000001010110011 3
b10000101000001010110011 V
b10000101000001010110011 !"
b11000 S
b11000 c
b11000 h
b11000 n
b10100 (
b10100 1
b10100 U
b10100 d
b10100 g
b10100 l
b10100 ~
1$
#75
0$
#80
b1001000 R
b1001000 f
b1001000 i
b110000 W
b110000 a
b110000 e
b110000 y
b1 7
b1 ?
b1 D
b1 J
b1 Y
b1000 P
b1000 p
b1000 u
b11 N
b11 [
b11 z
0.
b10 4
b10 <
b10 G
b10 K
b10 _
1=
b1 >
b1 C
b1 H
0]
b11 !
b11 &
b11 ,
b11 M
b11 v
b11 x
b11 }
b1000001010 I
b1000 #
b1000 *
b1000 6
b1000 X
b1000 ^
b1000 m
b1000 {
b1 9
b1 A
b111 s
b1001110010100010000 `
b10000 t
b1100011 :
b1100011 B
b1100011 E
b11100 T
b11100 j
b11100 k
b1110 Z
b1011 O
b1011 \
b1011 w
b10011100101000100001100011 )
b10011100101000100001100011 3
b10011100101000100001100011 V
b10011100101000100001100011 !"
b11100 S
b11100 c
b11100 h
b11100 n
b11000 (
b11000 1
b11000 U
b11000 d
b11000 g
b11000 l
b11000 ~
1$
#85
0$
#90
b0 P
b0 p
b0 u
1+
0]
b111 N
b111 [
b111 z
b101 7
b101 ?
b101 D
b101 J
b101 Y
b0 #
b0 *
b0 6
b0 X
b0 ^
b0 m
b0 {
1.
bx 4
bx <
bx G
bx K
bx _
0=
b10 >
b10 C
b10 H
b111 !
b111 &
b111 ,
b111 M
b111 v
b111 x
b111 }
b10011 Z
b1100 O
b1100 \
b1100 w
bx W
bx a
bx e
bx y
b1xx00000100 I
b0 9
b0 A
b100 s
b11 r
b1000001101000100 `
b100 t
b10 8
b10 @
b110011 :
b110011 B
b110011 E
b100000 T
b100000 j
b100000 k
b10000011010001000110011 )
b10000011010001000110011 3
b10000011010001000110011 V
b10000011010001000110011 !"
bx R
bx f
bx i
b100000 S
b100000 c
b100000 h
b100000 n
b11100 (
b11100 1
b11100 U
b11100 d
b11100 g
b11100 l
b11100 ~
1$
#95
0$
#100
10
b101000 R
b101000 f
b101000 i
b1000 W
b1000 a
b1000 e
b1000 y
b1 7
b1 ?
b1 D
b1 J
b1 Y
0.
b10 4
b10 <
b10 G
b10 K
b10 _
1=
b1 >
b1 C
b1 H
b0 O
b0 \
b0 w
b1000001010 I
b0 Z
b0 N
b0 [
b0 z
b0 s
b10000001000 `
b1000 t
b100 r
b0 8
b0 @
b1100011 :
b1100011 B
b1100011 E
b101000 T
b101000 j
b101000 k
b0 !
b0 &
b0 ,
b0 M
b0 v
b0 x
b0 }
b100000010001100011 )
b100000010001100011 3
b100000010001100011 V
b100000010001100011 !"
b100100 S
b100100 c
b100100 h
b100100 n
b100000 (
b100000 1
b100000 U
b100000 d
b100000 g
b100000 l
b100000 ~
1$
#105
0$
#110
b1 P
b1 p
b1 u
00
1]
b101 N
b101 [
b101 z
b101 7
b101 ?
b101 D
b101 J
b101 Y
0+
b1 #
b1 *
b1 6
b1 X
b1 ^
b1 m
b1 {
1.
bx 4
bx <
bx G
bx K
bx _
0=
b10 >
b10 C
b10 H
b101 !
b101 &
b101 ,
b101 M
b101 v
b101 x
b101 }
bx W
bx a
bx e
bx y
b1000 Z
b11 O
b11 \
b11 w
b1xx00000100 I
b10 s
b100011101000100 `
b100 t
b111 r
b10 8
b10 @
b110011 :
b110011 B
b110011 E
b101100 T
b101100 j
b101100 k
b1000111010001000110011 )
b1000111010001000110011 3
b1000111010001000110011 V
b1000111010001000110011 !"
bx R
bx f
bx i
b101100 S
b101100 c
b101100 h
b101100 n
b101000 (
b101000 1
b101000 U
b101000 d
b101000 g
b101000 l
b101000 ~
1$
#115
0$
#120
b1100 P
b1100 p
b1100 u
0]
b1011 N
b1011 [
b1011 z
b1100 #
b1100 *
b1100 6
b1100 X
b1100 ^
b1100 m
b1100 {
b1011 !
b1011 &
b1011 ,
b1011 M
b1011 v
b1011 x
b1011 }
b1100 Z
b1 O
b1 \
b1 w
b0 7
b0 ?
b0 D
b0 J
b0 Y
b101 s
b100 r
b0 8
b0 @
b1010010000000111 `
b111 t
b110000 T
b110000 j
b110000 k
b10100100000001110110011 )
b10100100000001110110011 3
b10100100000001110110011 V
b10100100000001110110011 !"
b110000 S
b110000 c
b110000 h
b110000 n
b101100 (
b101100 1
b101100 U
b101100 d
b101100 g
b101100 l
b101100 ~
1$
#125
0$
#130
b111 P
b111 p
b111 u
1]
b101 N
b101 [
b101 z
b111 #
b111 *
b111 6
b111 X
b111 ^
b111 m
b111 {
b1 7
b1 ?
b1 D
b1 J
b1 Y
b101 !
b101 &
b101 ,
b101 M
b101 v
b101 x
b101 }
b10001 Z
b1100 O
b1100 \
b1100 w
b100000 9
b100000 A
b10 s
b100000000100011100000111 `
b111 r
b110100 T
b110100 j
b110100 k
b1000000001000111000001110110011 )
b1000000001000111000001110110011 3
b1000000001000111000001110110011 V
b1000000001000111000001110110011 !"
b110100 S
b110100 c
b110100 h
b110100 n
b110000 (
b110000 1
b110000 U
b110000 d
b110000 g
b110000 l
b110000 ~
1$
#135
0$
#140
b10001000 R
b10001000 f
b10001000 i
b1010100 W
b1010100 a
b1010100 e
b1010100 y
b1100000 P
b1100000 p
b1100000 u
b1010100 N
b1010100 [
b1010100 z
0.
b1 4
b1 <
b1 G
b1 K
b1 _
15
1"
b0 >
b0 C
b0 H
0+
0]
b111 !
b111 &
b111 ,
b111 M
b111 v
b111 x
b111 }
b111000000 I
b0 7
b0 ?
b0 D
b0 J
b0 Y
b1100000 #
b1100000 *
b1100000 6
b1100000 X
b1100000 ^
b1100000 m
b1100000 {
b10 9
b10 A
b111 s
b11 r
b10 8
b10 @
b10001110001101010100 `
b10100 t
b100011 :
b100011 B
b100011 E
b111000 T
b111000 j
b111000 k
b1100000 Z
b1100 O
b1100 \
b1100 w
b100011100011010101000100011 )
b100011100011010101000100011 3
b100011100011010101000100011 V
b100011100011010101000100011 !"
b111000 S
b111000 c
b111000 h
b111000 n
b110100 (
b110100 1
b110100 U
b110100 d
b110100 g
b110100 l
b110100 ~
1$
#145
0$
#150
b111 P
b111 p
b111 u
b1100000 N
b1100000 [
b1100000 z
b1100000 #
b1100000 *
b1100000 6
b1100000 X
b1100000 ^
b1100000 m
b1100000 {
1.
b0 4
b0 <
b0 G
b0 K
b0 _
0"
b1 -
b1 ;
b1 F
b1 L
b1 o
b0 !
b0 &
b0 ,
b0 M
b0 v
b0 x
b0 }
b1100000 W
b1100000 a
b1100000 e
b1100000 y
b1100000 Z
b0 O
b0 \
b0 w
b10010010000 I
b11 9
b11 A
b0 s
b11000000000001000010 `
b10 t
b0 r
b11 :
b11 B
b11 E
b111100 T
b111100 j
b111100 k
b110000000000010000100000011 )
b110000000000010000100000011 3
b110000000000010000100000011 V
b110000000000010000100000011 !"
b10011000 R
b10011000 f
b10011000 i
b111100 S
b111100 c
b111100 h
b111100 n
b111000 (
b111000 1
b111000 U
b111000 d
b111000 g
b111000 l
b111000 ~
b111 '
b111 /
b111 Q
b111 q
b111 |
1$
#155
0$
#160
b10010 P
b10010 p
b10010 u
bx '
bx /
bx Q
bx q
bx |
b10010 #
b10010 *
b10010 6
b10010 X
b10010 ^
b10010 m
b10010 {
b1011 N
b1011 [
b1011 z
bx 4
bx <
bx G
bx K
bx _
05
b0 -
b0 ;
b0 F
b0 L
b0 o
b10 >
b10 C
b10 H
b1011 !
b1011 &
b1011 ,
b1011 M
b1011 v
b1011 x
b1011 }
b10010 Z
b111 O
b111 \
b111 w
bx W
bx a
bx e
bx y
b1xx00000100 I
b0 9
b0 A
b101 s
b10 r
b0 8
b0 @
b1010001000001001 `
b1001 t
b110011 :
b110011 B
b110011 E
b1000000 T
b1000000 j
b1000000 k
b10100010000010010110011 )
b10100010000010010110011 3
b10100010000010010110011 V
b10100010000010010110011 !"
bx R
bx f
bx i
b1000000 S
b1000000 c
b1000000 h
b1000000 n
b111100 (
b111100 1
b111100 U
b111100 d
b111100 g
b111100 l
b111100 ~
1$
#165
0$
#170
b1111110 P
b1111110 p
b1111110 u
b111 N
b111 [
b111 z
b1111110 #
b1111110 *
b1111110 6
b1111110 X
b1111110 ^
b1111110 m
b1111110 {
b1001 7
b1001 ?
b1001 D
b1001 J
b1001 Y
b111 !
b111 &
b111 ,
b111 M
b111 v
b111 x
b111 }
b11001 Z
b10010 O
b10010 \
b10010 w
b1 9
b1 A
b10 s
b1001 r
b1000100100100001010 `
b1010 t
b1000100 T
b1000100 j
b1000100 k
b10001001001000010100110011 )
b10001001001000010100110011 3
b10001001001000010100110011 V
b10001001001000010100110011 !"
b1000100 S
b1000100 c
b1000100 h
b1000100 n
b1000000 (
b1000000 1
b1000000 U
b1000000 d
b1000000 g
b1000000 l
b1000000 ~
1$
#175
0$
