decoders/ALU decoder/ALU_decoder2.sv
module ALU_decoder2(input logic  [1:0] ALUOp,
                    input logic [2:0] funct3,
                    input logic       opb5,
                    input logic [6:0] funct7,
                    
                    output logic [3:0] ALUControl);
    
   
    always_comb

        case(ALUOp)
            2'b00:                      ALUControl = 4'b0000; // performs addition;
            2'b01:                       ALUControl = 4'b0001; // performs subtraction;
            default: case(funct3)
                    3'b000: 
                        case(funct7)
                            7'b0000000:         ALUControl = 4'b0000; // add,addi;
                            7'b0000001:         ALUControl = 4'b1001; // multiply;
                            7'b0100000:         ALUControl = 4'b0001; // R type subtraction;
                        endcase
                    3'b010:                 ALUControl = 4'b0101; // set less than,slti;
                    3'b110:                 ALUControl = 4'b0011; // or,ori;
                    3'b111:                 ALUControl = 4'b0010; // and,andi;
                    3'b100:                 ALUControl = 4'b0100; // divide(signed)
                    3'b101: if (funct7 == 7'b0100000)        
                                            ALUControl = 4'b0110; // shift right arithmetic
                            else
                                            ALUControl = 4'b0111; // shift right logical
                    3'b001:                 ALUControl = 4'b1000; // shift left logical
                    default:                ALUControl = 4'bxxxx; // ???
            endcase
        endcase
endmodule

decoders/ALU decoder/ALU_decoder2_tb.sv
`timescale 1ps/1ps
`include "ALU_decoder2.sv"
module ALU_decoder2_tb;
logic  [1:0] ALUOp;
logic  [2:0] funct3;
logic       opb5;
logic  [6:0] funct7;
logic  [3:0] ALUControl;

ALU_decoder2 dut (ALUOp,funct3,opb5,funct7,ALUControl);


initial begin // Apply stimulus
$dumpfile("ALU_decoder2_tb.vcd");
$dumpvars(0, ALU_decoder2_tb);

ALUOp = 00;
#10 ALUOp = 01;
#10 ALUOp = 10; funct3 = 3'b010;
#10 funct3 = 3'b110;
#10 funct3 = 3'b111;
#10 funct3 = 3'b100;
#10 funct3 = 3'b001;
#10 funct3 = 3'b101; funct7 = 7'b0100000;
#10 funct7 = 7'b0000000;
#10 funct3 = 3'b000; funct7 = 7'b0100000; opb5 = 1;
#10 funct7 = 7'b0000000; opb5 = 0;
#10 funct7 = 7'b0000001;

$finish; // This system tasks ends the simulation
end
initial begin // Response monitor
$monitor ("t = %3d, ALUOp = %b, funct3 = %b, opb5 = %b, funct7 = %b, ALUControl = %b", $time, ALUOp, funct3, opb5, funct7, ALUControl);
end
endmodule

decoders/ALU decoder/ALU_decoder2_tb.vcd
$date
	Fri Dec 23 01:03:48 2022
$end
$version
	Icarus Verilog
$end
$timescale
	1ps
$end
$scope module ALU_decoder2_tb $end
$var wire 4 ! ALUControl [3:0] $end
$var reg 2 " ALUOp [1:0] $end
$var reg 3 # funct3 [2:0] $end
$var reg 7 $ funct7 [6:0] $end
$var reg 1 % opb5 $end
$scope module dut $end
$var wire 2 & ALUOp [1:0] $end
$var wire 3 ' funct3 [2:0] $end
$var wire 7 ( funct7 [6:0] $end
$var wire 1 % opb5 $end
$var reg 4 ) ALUControl [3:0] $end
$upscope $end
$upscope $end
$enddefinitions $end
#0
$dumpvars
b0 )
bx (
bx '
b0 &
x%
bx $
bx #
b0 "
b0 !
$end
#10
b1 !
b1 )
b1 "
b1 &
#20
b101 !
b101 )
b10 #
b10 '
b10 "
b10 &
#30
b11 !
b11 )
b110 #
b110 '
#40
b10 !
b10 )
b111 #
b111 '
#50
b100 !
b100 )
b100 #
b100 '
#60
b1000 !
b1000 )
b1 #
b1 '
#70
b110 !
b110 )
b100000 $
b100000 (
b101 #
b101 '
#80
b111 !
b111 )
b0 $
b0 (
#90
b1 !
b1 )
1%
b100000 $
b100000 (
b0 #
b0 '
#100
b0 !
b0 )
0%
b0 $
b0 (
#110
b1001 !
b1001 )
b1 $
b1 (
