ALU modules/Adder/adder.sv
module adder(input logic  [31:0] a,
             input logic  [31:0] b,
             output logic  [31:0] c,
             output logic C_out);
  //logic [32:0] y_test;
    assign {C_out,c} = a + b;
                                      
  
endmodule

ALU modules/Adder/adder_tb.sv
`timescale 1ps/1ps
`include "adder.sv"
module adder_tb;
logic  [31:0] a, b;
logic  [31:0] c;
logic C_out;

adder dut (a,b,c,C_out);


initial begin // Apply stimulus
$dumpfile("adder_tb.vcd");
$dumpvars(0, adder_tb);
a = 0; b = 0; 

#10 a = -1;
#15 b = -1;
#20 a = 1;
#10 a = 2147483648;
#10 b = 2147483648;
#10 a = 4294967296;
#10 b = 4294967296;



$finish; // This system tasks ends the simulation
end
initial begin // Response monitor
$monitor ("t = %3d, a = %b, b = %b, c = %b, C_out = %b", $time, a,b,c,C_out);
end
endmodule

ALU modules/Adder/adder_tb.vcd
$date
	Wed Nov 16 16:53:06 2022
$end
$version
	Icarus Verilog
$end
$timescale
	1ps
$end
$scope module adder_tb $end
$var wire 32 ! c [31:0] $end
$var wire 1 " C_out $end
$var reg 32 # a [31:0] $end
$var reg 32 $ b [31:0] $end
$scope module dut $end
$var wire 32 % a [31:0] $end
$var wire 32 & b [31:0] $end
$var wire 32 ' c [31:0] $end
$var wire 1 " C_out $end
$upscope $end
$upscope $end
$enddefinitions $end
#0
$dumpvars
b0 '
b0 &
b0 %
b0 $
b0 #
0"
b0 !
$end
#10
b11111111111111111111111111111111 !
b11111111111111111111111111111111 '
b11111111111111111111111111111111 #
b11111111111111111111111111111111 %
#25
b11111111111111111111111111111110 !
b11111111111111111111111111111110 '
1"
b11111111111111111111111111111111 $
b11111111111111111111111111111111 &
#45
b0 !
b0 '
b1 #
b1 %
#55
b1111111111111111111111111111111 !
b1111111111111111111111111111111 '
b10000000000000000000000000000000 #
b10000000000000000000000000000000 %
#65
b0 !
b0 '
b10000000000000000000000000000000 $
b10000000000000000000000000000000 &
#75
b10000000000000000000000000000000 !
b10000000000000000000000000000000 '
0"
b0 #
b0 %
#85
b0 !
b0 '
b0 $
b0 &
